go_concise_summary/__init__.py
go_concise_summary/main.py
go_concise_summary/prompts.py
go_concise_summary-2025.12.21141123.dist-info/METADATA
go_concise_summary-2025.12.21141123.dist-info/WHEEL
go_concise_summary-2025.12.21141123.dist-info/top_level.txt
go_concise_summary-2025.12.21141123.dist-info/RECORD
