Metadata-Version: 2.4
Name: go-concise-summary
Version: 2025.12.21141123
Summary: A new package would take a technical description or code snippet related to concurrency in Go and generate a structured summary of the concept, such as a fair, cancelable semaphore. It would extract k
Author-email: go-concise-summary <hi@eugene.plus>
License: MIT
Project-URL: Homepage, https://github.com/chigwell/go-concise-summary
Requires-Python: >=3.9
Requires-Dist: langchain-llm7>=0.0.0
Requires-Dist: llmatch-messages>=0.0.0
Requires-Dist: langchain-core>=0.3.0
